setup.py
SGA_TEST_1825/__init__.py
SGA_TEST_1825/extract.py
SGA_TEST_1825.egg-info/PKG-INFO
SGA_TEST_1825.egg-info/SOURCES.txt
SGA_TEST_1825.egg-info/dependency_links.txt
SGA_TEST_1825.egg-info/top_level.txt