Metadata-Version: 1.0
Name: SGA-TEST-1825
Version: 0.1.0
Summary: An package that tells you whether input string is numeric, alphabetic or alphanumeric
Home-page: UNKNOWN
Author: Tanish
Author-email: tanish.sanghvi@sganalytics.com
License: LICENSE.txt
Platform: UNKNOWN
